[
  {
    "scenario_id": "ss_mmu0vmkm7rln",
    "related_type": "graph",
    "related_id": "eg_mmu0uuaprnxu",
    "lane": "dev",
    "overrides": {},
    "created_at": "2026-03-17T02:58:02.374Z"
  },
  {
    "scenario_id": "ss_mmu0vmkjn8fu",
    "related_type": "graph",
    "related_id": "eg_mmu0uuaprnxu",
    "lane": "beta",
    "overrides": {
      "lane": "beta",
      "review_verdicts": {
        "quality": "fail"
      }
    },
    "created_at": "2026-03-17T02:58:02.371Z"
  },
  {
    "scenario_id": "ss_mmu0vmkig4te",
    "related_type": "graph",
    "related_id": "eg_mmu0uuaprnxu",
    "lane": "dev",
    "overrides": {
      "policies": {
        "review_strictness": "strict"
      }
    },
    "created_at": "2026-03-17T02:58:02.370Z"
  },
  {
    "scenario_id": "ss_mmu0vmkhtmrh",
    "related_type": "graph",
    "related_id": "eg_mmu0uuaprnxu",
    "lane": "dev",
    "overrides": {
      "provider_confidence": 30
    },
    "created_at": "2026-03-17T02:58:02.369Z"
  },
  {
    "scenario_id": "ss_mmu0vmkfhoqb",
    "related_type": "graph",
    "related_id": "eg_mmu0uuaprnxu",
    "lane": "prod",
    "overrides": {
      "lane": "prod",
      "documentation_missing": [
        "architecture_doc",
        "runbook"
      ]
    },
    "created_at": "2026-03-17T02:58:02.367Z"
  },
  {
    "scenario_id": "ss_mmu0vmkdw0q2",
    "related_type": "graph",
    "related_id": "eg_mmu0uuaprnxu",
    "lane": "prod",
    "overrides": {
      "lane": "prod"
    },
    "created_at": "2026-03-17T02:58:02.365Z"
  },
  {
    "scenario_id": "ss_mmu0vmkbabk7",
    "related_type": "graph",
    "related_id": "eg_mmu0uuaprnxu",
    "lane": "beta",
    "overrides": {
      "lane": "beta"
    },
    "created_at": "2026-03-17T02:58:02.363Z"
  },
  {
    "scenario_id": "ss_mmu0vmk7tl4b",
    "related_type": "graph",
    "related_id": "eg_mmu0uuaprnxu",
    "lane": "dev",
    "overrides": {},
    "created_at": "2026-03-17T02:58:02.359Z"
  },
  {
    "scenario_id": "ss_mmu0v9swrij0",
    "related_type": "graph",
    "related_id": "eg_mmu0uuaprnxu",
    "lane": "dev",
    "overrides": {},
    "created_at": "2026-03-17T02:57:45.824Z"
  },
  {
    "scenario_id": "ss_mmu0v9su358q",
    "related_type": "graph",
    "related_id": "eg_mmu0uuaprnxu",
    "lane": "beta",
    "overrides": {
      "lane": "beta",
      "review_verdicts": {
        "quality": "fail"
      }
    },
    "created_at": "2026-03-17T02:57:45.822Z"
  },
  {
    "scenario_id": "ss_mmu0v9sukw5p",
    "related_type": "graph",
    "related_id": "eg_mmu0uuaprnxu",
    "lane": "dev",
    "overrides": {
      "policies": {
        "review_strictness": "strict"
      }
    },
    "created_at": "2026-03-17T02:57:45.822Z"
  },
  {
    "scenario_id": "ss_mmu0v9stx63n",
    "related_type": "graph",
    "related_id": "eg_mmu0uuaprnxu",
    "lane": "dev",
    "overrides": {
      "provider_confidence": 30
    },
    "created_at": "2026-03-17T02:57:45.821Z"
  },
  {
    "scenario_id": "ss_mmu0v9strb3n",
    "related_type": "graph",
    "related_id": "eg_mmu0uuaprnxu",
    "lane": "prod",
    "overrides": {
      "lane": "prod",
      "documentation_missing": [
        "architecture_doc",
        "runbook"
      ]
    },
    "created_at": "2026-03-17T02:57:45.821Z"
  },
  {
    "scenario_id": "ss_mmu0v9ss9uwv",
    "related_type": "graph",
    "related_id": "eg_mmu0uuaprnxu",
    "lane": "prod",
    "overrides": {
      "lane": "prod"
    },
    "created_at": "2026-03-17T02:57:45.820Z"
  },
  {
    "scenario_id": "ss_mmu0v9sr8eld",
    "related_type": "graph",
    "related_id": "eg_mmu0uuaprnxu",
    "lane": "beta",
    "overrides": {
      "lane": "beta"
    },
    "created_at": "2026-03-17T02:57:45.819Z"
  },
  {
    "scenario_id": "ss_mmu0v9sfwpkq",
    "related_type": "graph",
    "related_id": "eg_mmu0uuaprnxu",
    "lane": "dev",
    "overrides": {},
    "created_at": "2026-03-17T02:57:45.807Z"
  }
]